{
  "project_info": {
    "project_number": "604959073240",
    "project_id": "elearning-f2392",
    "storage_bucket": "elearning-f2392.appspot.com"
  },
  "client": [
    {
      "client_info": {
        "mobilesdk_app_id": "1:604959073240:android:0eaf31d59458ca79e748ad",
        "android_client_info": {
          "package_name": "com.example.elearning"
        }
      },
      "oauth_client": [],
      "api_key": [
        {
          "current_key": "AIzaSyAW2G_zr1YJUuQa4myYoNDp1JMiyIuvY8Q"
        }
      ],
      "services": {
        "appinvite_service": {
          "other_platform_oauth_client": []
        }
      }
    }
  ],
  "configuration_version": "1"
}